py_ark_vrf-0.3.0.dist-info/METADATA
py_ark_vrf-0.3.0.dist-info/WHEEL
py_ark_vrf/__init__.py
py_ark_vrf/__init__.pyi
py_ark_vrf/bandersnatch_ring.srs
py_ark_vrf/py.typed
py_ark_vrf/py_ark_vrf.cpython-313-x86_64-linux-gnu.so
py_ark_vrf-0.3.0.dist-info/RECORD
