Metadata-Version: 2.4
Name: py_ark_vrf
Version: 0.3.0
Summary: Python bindings for ark-vrf
Author-email: Prasad <prasad@chainscore.finance>
Requires-Python: >=3.8
Project-URL: Homepage, https://github.com/chainscore/py-ark-vrf
Project-URL: Bug Tracker, https://github.com/chainscore/py-ark-vrf/issues
